{
  "imageWidth": 3648,
  "imagePath": "samples/untagged/dscn2374.jpg",
  "areas": [{
    "area": [
      {
        "x": 1992.719970703125,
        "y": 1012.3200073242188
      },
      {
        "x": 2042.8800048828125,
        "y": 980.4000244140625
      },
      {
        "x": 2006.4000244140625,
        "y": 962.1599731445312
      },
      {
        "x": 2020.0799560546875,
        "y": 912
      },
      {
        "x": 1965.3599853515625,
        "y": 916.5599975585938
      },
      {
        "x": 1983.5999755859375,
        "y": 893.760009765625
      },
      {
        "x": 1960.800048828125,
        "y": 866.4000244140625
      },
      {
        "x": 1901.52001953125,
        "y": 884.6400146484375
      },
      {
        "x": 1910.6400146484375,
        "y": 943.9199829101562
      },
      {
        "x": 1992.719970703125,
        "y": 1012.3200073242188
      }
    ],
    "type": "Carta/Cartone"
  }],
  "imageHeight": 2736
}