{
  "imageWidth": 3648,
  "imagePath": "samples/untagged/dscn1630.jpg",
  "areas": [
    {
      "area": [
        {
          "x": 2097.60009765625,
          "y": 1317.8399658203125
        },
        {
          "x": 1969.9200439453125,
          "y": 1445.52001953125
        },
        {
          "x": 1842.239990234375,
          "y": 1518.47998046875
        },
        {
          "x": 1787.52001953125,
          "y": 1559.52001953125
        },
        {
          "x": 1755.5999755859375,
          "y": 1518.47998046875
        },
        {
          "x": 1646.1600341796875,
          "y": 1545.8399658203125
        },
        {
          "x": 1586.8800048828125,
          "y": 1459.199951171875
        },
        {
          "x": 1586.8800048828125,
          "y": 1459.199951171875
        },
        {
          "x": 1700.8800048828125,
          "y": 1399.9200439453125
        },
        {
          "x": 1691.760009765625,
          "y": 1358.8800048828125
        },
        {
          "x": 2006.4000244140625,
          "y": 1149.1199951171875
        },
        {
          "x": 2065.679931640625,
          "y": 1158.239990234375
        },
        {
          "x": 2115.840087890625,
          "y": 1249.43994140625
        },
        {
          "x": 2083.919921875,
          "y": 1317.8399658203125
        },
        {
          "x": 2097.60009765625,
          "y": 1317.8399658203125
        }
      ],
      "type": "Plastica"
    },
    {
      "area": [
        {
          "x": 702.239990234375,
          "y": 492.4800109863281
        },
        {
          "x": 606.47998046875,
          "y": 442.32000732421875
        },
        {
          "x": 633.8400268554688,
          "y": 337.44000244140625
        },
        {
          "x": 670.3200073242188,
          "y": 296.3999938964844
        },
        {
          "x": 784.3200073242188,
          "y": 259.9200134277344
        },
        {
          "x": 820.7999877929688,
          "y": 346.55999755859375
        },
        {
          "x": 820.7999877929688,
          "y": 383.0400085449219
        },
        {
          "x": 820.7999877929688,
          "y": 396.7200012207031
        },
        {
          "x": 738.719970703125,
          "y": 460.55999755859375
        },
        {
          "x": 802.5599975585938,
          "y": 510.7200012207031
        },
        {
          "x": 706.7999877929688,
          "y": 501.6000061035156
        },
        {
          "x": 702.239990234375,
          "y": 492.4800109863281
        }
      ],
      "type": "Plastica"
    }
  ],
  "imageHeight": 2736
}