{
  "imageWidth": 3648,
  "imagePath": "samples/untagged/dscn1991.jpg",
  "areas": [
    {
      "area": [
        {
          "x": 2056.56005859375,
          "y": 1144.56005859375
        },
        {
          "x": 2124.9599609375,
          "y": 1135.43994140625
        },
        {
          "x": 2170.56005859375,
          "y": 1171.9200439453125
        },
        {
          "x": 2188.800048828125,
          "y": 1240.3199462890625
        },
        {
          "x": 2115.840087890625,
          "y": 1340.6400146484375
        },
        {
          "x": 2079.360107421875,
          "y": 1440.9599609375
        },
        {
          "x": 2015.52001953125,
          "y": 1532.1600341796875
        },
        {
          "x": 1974.47998046875,
          "y": 1550.4000244140625
        },
        {
          "x": 1910.6400146484375,
          "y": 1527.5999755859375
        },
        {
          "x": 1878.719970703125,
          "y": 1486.56005859375
        },
        {
          "x": 1865.0400390625,
          "y": 1459.199951171875
        },
        {
          "x": 1865.0400390625,
          "y": 1445.52001953125
        },
        {
          "x": 1919.760009765625,
          "y": 1349.760009765625
        },
        {
          "x": 1983.5999755859375,
          "y": 1267.6800537109375
        },
        {
          "x": 2020.0799560546875,
          "y": 1199.280029296875
        },
        {
          "x": 2056.56005859375,
          "y": 1144.56005859375
        }
      ],
      "type": "Alluminio"
    },
    {
      "area": [
        {
          "x": 975.8400268554688,
          "y": 255.36000061035156
        },
        {
          "x": 1016.8800048828125,
          "y": 255.36000061035156
        },
        {
          "x": 1103.52001953125,
          "y": 264.4800109863281
        },
        {
          "x": 1126.3199462890625,
          "y": 218.8800048828125
        },
        {
          "x": 998.6400146484375,
          "y": 186.9600067138672
        },
        {
          "x": 975.8400268554688,
          "y": 255.36000061035156
        }
      ],
      "type": "Carta/Cartone"
    }
  ],
  "imageHeight": 2736
}