{
  "imageWidth": 3648,
  "imagePath": "samples/untagged/dscn2679.jpg",
  "areas": [
    {
      "area": [
        {
          "x": 1988.1600341796875,
          "y": 1126.3199462890625
        },
        {
          "x": 2147.760009765625,
          "y": 1258.56005859375
        },
        {
          "x": 2193.360107421875,
          "y": 1276.800048828125
        },
        {
          "x": 2339.280029296875,
          "y": 1285.9200439453125
        },
        {
          "x": 2343.840087890625,
          "y": 1171.9200439453125
        },
        {
          "x": 2316.47998046875,
          "y": 1144.56005859375
        },
        {
          "x": 2298.239990234375,
          "y": 1117.199951171875
        },
        {
          "x": 2266.320068359375,
          "y": 1117.199951171875
        },
        {
          "x": 2147.760009765625,
          "y": 1030.56005859375
        },
        {
          "x": 2134.080078125,
          "y": 962.1599731445312
        },
        {
          "x": 2097.60009765625,
          "y": 971.280029296875
        },
        {
          "x": 2079.360107421875,
          "y": 966.719970703125
        },
        {
          "x": 2010.9599609375,
          "y": 1062.47998046875
        },
        {
          "x": 2020.0799560546875,
          "y": 1085.280029296875
        },
        {
          "x": 1988.1600341796875,
          "y": 1126.3199462890625
        }
      ],
      "type": "Plastica"
    },
    {
      "area": [
        {
          "x": 1431.8399658203125,
          "y": 811.6799926757812
        },
        {
          "x": 1436.4000244140625,
          "y": 747.8400268554688
        },
        {
          "x": 1513.9200439453125,
          "y": 720.47998046875
        },
        {
          "x": 1541.280029296875,
          "y": 706.7999877929688
        },
        {
          "x": 1600.56005859375,
          "y": 756.9600219726562
        },
        {
          "x": 1564.0799560546875,
          "y": 834.47998046875
        },
        {
          "x": 1559.52001953125,
          "y": 756.9600219726562
        },
        {
          "x": 1500.239990234375,
          "y": 793.4400024414062
        },
        {
          "x": 1431.8399658203125,
          "y": 811.6799926757812
        }
      ],
      "type": "Carta/Cartone"
    }
  ],
  "imageHeight": 2736
}