{
  "imageWidth": 3648,
  "imagePath": "samples/untagged/dscn2352.jpg",
  "areas": [
    {
      "area": [
        {
          "x": 533.52001953125,
          "y": 177.83999633789062
        },
        {
          "x": 506.1600036621094,
          "y": 22.799999237060547
        },
        {
          "x": 570,
          "y": 22.799999237060547
        },
        {
          "x": 601.9199829101562,
          "y": 22.799999237060547
        },
        {
          "x": 624.719970703125,
          "y": 13.680000305175781
        },
        {
          "x": 898.3200073242188,
          "y": 4.559999942779541
        },
        {
          "x": 884.6400146484375,
          "y": 86.63999938964844
        },
        {
          "x": 962.1599731445312,
          "y": 118.55999755859375
        },
        {
          "x": 939.3599853515625,
          "y": 177.83999633789062
        },
        {
          "x": 533.52001953125,
          "y": 177.83999633789062
        }
      ],
      "type": "Carta/Cartone"
    },
    {
      "area": [
        {
          "x": 1869.5999755859375,
          "y": 875.52001953125
        },
        {
          "x": 2042.8800048828125,
          "y": 912
        },
        {
          "x": 2202.47998046875,
          "y": 588.239990234375
        },
        {
          "x": 2152.320068359375,
          "y": 501.6000061035156
        },
        {
          "x": 2115.840087890625,
          "y": 469.67999267578125
        },
        {
          "x": 2083.919921875,
          "y": 469.67999267578125
        },
        {
          "x": 2061.1201171875,
          "y": 487.9200134277344
        },
        {
          "x": 2015.52001953125,
          "y": 538.0800170898438
        },
        {
          "x": 1965.3599853515625,
          "y": 510.7200012207031
        },
        {
          "x": 1928.8800048828125,
          "y": 533.52001953125
        },
        {
          "x": 1878.719970703125,
          "y": 533.52001953125
        },
        {
          "x": 1837.6800537109375,
          "y": 611.0399780273438
        },
        {
          "x": 1855.9200439453125,
          "y": 670.3200073242188
        },
        {
          "x": 1869.5999755859375,
          "y": 875.52001953125
        }
      ],
      "type": "Plastica"
    },
    {
      "area": [
        {
          "x": 1436.4000244140625,
          "y": 2275.43994140625
        },
        {
          "x": 1454.6400146484375,
          "y": 2352.9599609375
        },
        {
          "x": 1422.719970703125,
          "y": 2453.280029296875
        },
        {
          "x": 1550.4000244140625,
          "y": 2498.8798828125
        },
        {
          "x": 1641.5999755859375,
          "y": 2462.39990234375
        },
        {
          "x": 1737.3599853515625,
          "y": 2480.639892578125
        },
        {
          "x": 1810.3199462890625,
          "y": 2453.280029296875
        },
        {
          "x": 1851.3599853515625,
          "y": 2371.199951171875
        },
        {
          "x": 2033.760009765625,
          "y": 2270.8798828125
        },
        {
          "x": 1938,
          "y": 2193.360107421875
        },
        {
          "x": 1819.43994140625,
          "y": 2197.919921875
        },
        {
          "x": 1682.6400146484375,
          "y": 2129.52001953125
        },
        {
          "x": 1573.199951171875,
          "y": 2161.43994140625
        },
        {
          "x": 1436.4000244140625,
          "y": 2275.43994140625
        }
      ],
      "type": "Plastica"
    },
    {
      "area": [
        {
          "x": 2526.239990234375,
          "y": 1463.760009765625
        },
        {
          "x": 2293.679931640625,
          "y": 1290.47998046875
        },
        {
          "x": 2184.239990234375,
          "y": 1203.8399658203125
        },
        {
          "x": 2079.360107421875,
          "y": 1089.8399658203125
        },
        {
          "x": 2088.47998046875,
          "y": 1026
        },
        {
          "x": 2001.8399658203125,
          "y": 998.6400146484375
        },
        {
          "x": 1988.1600341796875,
          "y": 962.1599731445312
        },
        {
          "x": 1947.1199951171875,
          "y": 984.9600219726562
        },
        {
          "x": 1782.9599609375,
          "y": 957.5999755859375
        },
        {
          "x": 1687.199951171875,
          "y": 943.9199829101562
        },
        {
          "x": 1582.3199462890625,
          "y": 975.8400268554688
        },
        {
          "x": 1486.56005859375,
          "y": 1003.2000122070312
        },
        {
          "x": 1418.1600341796875,
          "y": 916.5599975585938
        },
        {
          "x": 1313.280029296875,
          "y": 912
        },
        {
          "x": 1281.3599853515625,
          "y": 934.7999877929688
        },
        {
          "x": 1249.43994140625,
          "y": 943.9199829101562
        },
        {
          "x": 1194.719970703125,
          "y": 1016.8800048828125
        },
        {
          "x": 1112.6400146484375,
          "y": 1094.4000244140625
        },
        {
          "x": 1039.6800537109375,
          "y": 1121.760009765625
        },
        {
          "x": 1071.5999755859375,
          "y": 1203.8399658203125
        },
        {
          "x": 1117.199951171875,
          "y": 1222.0799560546875
        },
        {
          "x": 1126.3199462890625,
          "y": 1345.199951171875
        },
        {
          "x": 1240.3199462890625,
          "y": 1358.8800048828125
        },
        {
          "x": 1295.0400390625,
          "y": 1336.0799560546875
        },
        {
          "x": 1381.6800537109375,
          "y": 1331.52001953125
        },
        {
          "x": 1390.800048828125,
          "y": 1354.3199462890625
        },
        {
          "x": 1039.6800537109375,
          "y": 1445.52001953125
        },
        {
          "x": 998.6400146484375,
          "y": 1568.6400146484375
        },
        {
          "x": 1217.52001953125,
          "y": 1796.6400146484375
        },
        {
          "x": 1254,
          "y": 1887.8399658203125
        },
        {
          "x": 1249.43994140625,
          "y": 1969.9200439453125
        },
        {
          "x": 1340.6400146484375,
          "y": 2042.8800048828125
        },
        {
          "x": 1381.6800537109375,
          "y": 2038.3199462890625
        },
        {
          "x": 1409.0400390625,
          "y": 2147.760009765625
        },
        {
          "x": 1445.52001953125,
          "y": 2184.239990234375
        },
        {
          "x": 1605.1199951171875,
          "y": 1919.760009765625
        },
        {
          "x": 1509.3599853515625,
          "y": 1851.3599853515625
        },
        {
          "x": 1399.9200439453125,
          "y": 1737.3599853515625
        },
        {
          "x": 1372.56005859375,
          "y": 1700.8800048828125
        },
        {
          "x": 1422.719970703125,
          "y": 1646.1600341796875
        },
        {
          "x": 1472.8800048828125,
          "y": 1632.47998046875
        },
        {
          "x": 1459.199951171875,
          "y": 1582.3199462890625
        },
        {
          "x": 1741.9200439453125,
          "y": 1504.800048828125
        },
        {
          "x": 1865.0400390625,
          "y": 1605.1199951171875
        },
        {
          "x": 1906.0799560546875,
          "y": 1591.43994140625
        },
        {
          "x": 1846.800048828125,
          "y": 1495.6800537109375
        },
        {
          "x": 1988.1600341796875,
          "y": 1399.9200439453125
        },
        {
          "x": 2038.3199462890625,
          "y": 1381.6800537109375
        },
        {
          "x": 2111.280029296875,
          "y": 1404.47998046875
        },
        {
          "x": 2343.840087890625,
          "y": 1431.8399658203125
        },
        {
          "x": 2526.239990234375,
          "y": 1463.760009765625
        }
      ],
      "type": "Plastica"
    }
  ],
  "imageHeight": 2736
}