{
  "imageHeight": 2736,
  "imagePath": "samples/untagged/dscn0057.jpg",
  "areas": [{
    "area": [
      {
        "y": 1285.9200439453125,
        "x": 1673.52001953125
      },
      {
        "y": 998.6400146484375,
        "x": 1801.199951171875
      },
      {
        "y": 1026,
        "x": 2070.239990234375
      },
      {
        "y": 1076.1600341796875,
        "x": 2106.719970703125
      },
      {
        "y": 1381.6800537109375,
        "x": 2056.56005859375
      },
      {
        "y": 1368,
        "x": 1919.760009765625
      },
      {
        "y": 1395.3599853515625,
        "x": 1883.280029296875
      },
      {
        "y": 1386.239990234375,
        "x": 1842.239990234375
      },
      {
        "y": 1431.8399658203125,
        "x": 1878.719970703125
      },
      {
        "y": 1409.0400390625,
        "x": 1792.0799560546875
      },
      {
        "y": 1349.760009765625,
        "x": 1810.3199462890625
      },
      {
        "y": 1322.4000244140625,
        "x": 1760.1600341796875
      },
      {
        "y": 1285.9200439453125,
        "x": 1673.52001953125
      }
    ],
    "type": "Plastica"
  }],
  "imageWidth": 3648
}